gazoo_device/__init__.py
gazoo_device/_version.py
gazoo_device/config.py
gazoo_device/console.py
gazoo_device/console_config.py
gazoo_device/custom_types.py
gazoo_device/data_types.py
gazoo_device/decorators.py
gazoo_device/detect_criteria.py
gazoo_device/device_detector.py
gazoo_device/errors.py
gazoo_device/extensions.py
gazoo_device/fire_manager.py
gazoo_device/fire_patch.py
gazoo_device/gazoo_device_controllers.py
gazoo_device/gdm_cli.py
gazoo_device/gdm_logger.py
gazoo_device/log_parser.py
gazoo_device/manager.py
gazoo_device/mobly_controller.py
gazoo_device/multiprocess_logging.py
gazoo_device/package_registrar.py
gazoo_device/testbed.py
gazoo_device/usb_port_map.py
gazoo_device/auxiliary_devices/__init__.py
gazoo_device/auxiliary_devices/cambrionix.py
gazoo_device/auxiliary_devices/dc2200.py
gazoo_device/auxiliary_devices/dli_powerswitch.py
gazoo_device/auxiliary_devices/dlink_switch.py
gazoo_device/auxiliary_devices/efr32.py
gazoo_device/auxiliary_devices/efr32_pigweed_lighting.py
gazoo_device/auxiliary_devices/esp32.py
gazoo_device/auxiliary_devices/esp32_pigweed_echo.py
gazoo_device/auxiliary_devices/esp32_pigweed_locking.py
gazoo_device/auxiliary_devices/m5stick.py
gazoo_device/auxiliary_devices/nrf52840.py
gazoo_device/auxiliary_devices/nrf_openthread.py
gazoo_device/auxiliary_devices/nrf_pigweed_lighting.py
gazoo_device/auxiliary_devices/raspberry_pi.py
gazoo_device/auxiliary_devices/raspberry_pi_matter_controller.py
gazoo_device/auxiliary_devices/unifi_poe_switch.py
gazoo_device/auxiliary_devices/yepkit.py
gazoo_device/base_classes/__init__.py
gazoo_device/base_classes/auxiliary_device.py
gazoo_device/base_classes/auxiliary_device_base.py
gazoo_device/base_classes/efr32_matter_device.py
gazoo_device/base_classes/esp32_matter_device.py
gazoo_device/base_classes/espressif_esp32_device.py
gazoo_device/base_classes/gazoo_device_base.py
gazoo_device/base_classes/matter_device_base.py
gazoo_device/base_classes/matter_endpoints_mixin.py
gazoo_device-1.123.0.dist-info/LICENSE
gazoo_device-1.123.0.dist-info/METADATA
gazoo_device-1.123.0.dist-info/WHEEL
gazoo_device-1.123.0.dist-info/entry_points.txt
gazoo_device-1.123.0.dist-info/top_level.txt
gazoo_device-1.123.0.dist-info/RECORD
