Metadata-Version: 2.1
Name: gazoo-device
Version: 1.123.0
Summary: Gazoo Device Manager
Home-page: https://github.com/google/gazoo-device
Author: Google LLC
Author-email: gdm-authors@google.com
License: Apache 2.0
Classifier: Development Status :: 5 - Production/Stable
Classifier: Intended Audience :: Developers
Classifier: License :: OSI Approved :: Apache Software License
Classifier: Operating System :: MacOS
Classifier: Operating System :: POSIX :: Linux
Classifier: Programming Language :: Python :: 3.9
Classifier: Programming Language :: Python :: 3.10
Classifier: Topic :: Software Development :: Embedded Systems
Classifier: Topic :: Software Development :: Libraries :: Python Modules
Classifier: Topic :: Software Development :: Testing
Requires-Python: >=3.9
License-File: LICENSE
Requires-Dist: fire (>=0.2.1)
Requires-Dist: immutabledict (>=2.0.0)
Requires-Dist: intelhex (>=2.2.1)
Requires-Dist: pigweed (>=0.0.3)
Requires-Dist: prompt-toolkit (>=3.0.19)
Requires-Dist: protobuf (<3.21.0,>=3.17.3)
Requires-Dist: psutil (>=5.0.1)
Requires-Dist: pylibftdi (>=0.19.0)
Requires-Dist: pylink-square (>=0.3.0)
Requires-Dist: pyserial (>=3.5)
Requires-Dist: pyudev (>=0.22.0)
Requires-Dist: pyusb (>=1.2.1)
Requires-Dist: pyvisa (>=1.12.0)
Requires-Dist: pyvisa-py (>=0.5.3)
Requires-Dist: requests (>=2.25.0)
Requires-Dist: urllib3 (>=1.26.3)
Requires-Dist: websocket-client (>=0.56.0)
Requires-Dist: xmodem (>=0.4.5)
